spark_scaffolder_transforms_tools/__init__.py
spark_scaffolder_transforms_tools/functions/__init__.py
spark_scaffolder_transforms_tools/functions/columns/__init__.py
spark_scaffolder_transforms_tools/functions/columns/autocast.py
spark_scaffolder_transforms_tools/functions/columns/clean_null.py
spark_scaffolder_transforms_tools/functions/columns/concat_columns.py
spark_scaffolder_transforms_tools/functions/columns/conditional.py
spark_scaffolder_transforms_tools/functions/columns/current_date.py
spark_scaffolder_transforms_tools/functions/columns/current_datetime.py
spark_scaffolder_transforms_tools/functions/columns/dateformat.py
spark_scaffolder_transforms_tools/functions/columns/dateformat_agg.py
spark_scaffolder_transforms_tools/functions/columns/dateformat_extract.py
spark_scaffolder_transforms_tools/functions/columns/dateformat_oper.py
spark_scaffolder_transforms_tools/functions/columns/drop_columns.py
spark_scaffolder_transforms_tools/functions/columns/drop_duplicates.py
spark_scaffolder_transforms_tools/functions/columns/filter_fields.py
spark_scaffolder_transforms_tools/functions/columns/filters.py
spark_scaffolder_transforms_tools/functions/columns/groupby.py
spark_scaffolder_transforms_tools/functions/columns/init_nulls.py
spark_scaffolder_transforms_tools/functions/columns/join.py
spark_scaffolder_transforms_tools/functions/columns/left_padding.py
spark_scaffolder_transforms_tools/functions/columns/offset_columns.py
spark_scaffolder_transforms_tools/functions/columns/pivot.py
spark_scaffolder_transforms_tools/functions/columns/rename_columns.py
spark_scaffolder_transforms_tools/functions/columns/replace.py
spark_scaffolder_transforms_tools/functions/columns/right_padding.py
spark_scaffolder_transforms_tools/functions/columns/select_columns.py
spark_scaffolder_transforms_tools/functions/columns/union.py
spark_scaffolder_transforms_tools/functions/rows/__init__.py
spark_scaffolder_transforms_tools/functions/rows/normalize_chars.py
spark_scaffolder_transforms_tools-0.0.1.dist-info/LICENSE
spark_scaffolder_transforms_tools-0.0.1.dist-info/METADATA
spark_scaffolder_transforms_tools-0.0.1.dist-info/WHEEL
spark_scaffolder_transforms_tools-0.0.1.dist-info/top_level.txt
spark_scaffolder_transforms_tools-0.0.1.dist-info/RECORD
