Metadata-Version: 2.1
Name: spark-scaffolder-transforms-tools
Version: 0.0.1
Summary: spark_scaffolder_transforms_tools
Home-page: https://github.com/jonaqp/spark_scaffolder_transforms_tools
Author: Jonathan Quiza
Author-email: jony327@gmail.com
License: UNKNOWN
Download-URL: https://github.com/jonaqp/spark_scaffolder_transforms_tools/archive/main.zip
Keywords: spark,scaffolder,pyspark
Platform: UNKNOWN
Classifier: Development Status :: 5 - Production/Stable
Classifier: Intended Audience :: Developers
Classifier: Intended Audience :: Science/Research
Classifier: Topic :: Scientific/Engineering :: Artificial Intelligence
Classifier: License :: OSI Approved :: Apache Software License
Classifier: Programming Language :: Python :: 3.9
Classifier: Programming Language :: Python :: 3.8
License-File: LICENSE
Requires-Dist: pandas (==2.0.1)
Requires-Dist: numpy (==1.24.3)
Requires-Dist: findspark (==2.0.1)
Requires-Dist: pyspark (==3.1.1)
Requires-Dist: pyarrow (==12.0.0)
Requires-Dist: setuptools (==58.2.0)
Requires-Dist: wheel (==0.40.0)
Requires-Dist: color-tools (>=0.0.2)
